{
  "node": {
    "00581040a59718f7d4c477f664180a07a0415fa92a": {
      "workers": {
        "app/card/manage/page": {
          "moduleId": 842951,
          "async": true,
          "exportedName": "getUserIDAll",
          "filename": "src/app/actions/manage.ts"
        }
      },
      "exportedName": "getUserIDAll",
      "filename": "src/app/actions/manage.ts"
    },
    "40a0826084565952bed5fdfa7c37fa8be6d0ce65f6": {
      "workers": {
        "app/card/manage/page": {
          "moduleId": 842951,
          "async": true,
          "exportedName": "getTagAll",
          "filename": "src/app/actions/card.ts"
        }
      },
      "exportedName": "getTagAll",
      "filename": "src/app/actions/card.ts"
    },
    "4078436741b7ef0cb9349351297c6cb384f5abce48": {
      "workers": {
        "app/card/manage/page": {
          "moduleId": 842951,
          "async": true,
          "exportedName": "saveCard",
          "filename": "src/app/actions/card.ts"
        }
      },
      "exportedName": "saveCard",
      "filename": "src/app/actions/card.ts"
    },
    "4027d05b4c621b1edaca5656b0f51bd65bb65395d4": {
      "workers": {
        "app/card/manage/page": {
          "moduleId": 842951,
          "async": true,
          "exportedName": "saveCardTag",
          "filename": "src/app/actions/card.ts"
        }
      },
      "exportedName": "saveCardTag",
      "filename": "src/app/actions/card.ts"
    },
    "6054503ff5ce5bb6ff3e7104e3d7a5a93708782e85": {
      "workers": {
        "app/card/manage/page": {
          "moduleId": 842951,
          "async": true,
          "exportedName": "getCardTag",
          "filename": "src/app/actions/card.ts"
        }
      },
      "exportedName": "getCardTag",
      "filename": "src/app/actions/card.ts"
    },
    "606787ebd758bdad132193e6f26c9df92383f4e709": {
      "workers": {
        "app/card/manage/page": {
          "moduleId": 842951,
          "async": true,
          "exportedName": "setCardFamiliarity",
          "filename": "src/app/actions/card.ts"
        }
      },
      "exportedName": "setCardFamiliarity",
      "filename": "src/app/actions/card.ts"
    },
    "7ec2b33e1e0da7629a8f90d8f68995759c3f38115e": {
      "workers": {
        "app/card/manage/page": {
          "moduleId": 842951,
          "async": true,
          "exportedName": "getCardAll",
          "filename": "src/app/actions/card.ts"
        }
      },
      "exportedName": "getCardAll",
      "filename": "src/app/actions/card.ts"
    },
    "60b067107240bdd4e684b56eab9cd7789de7638d41": {
      "workers": {
        "app/card/manage/page": {
          "moduleId": 842951,
          "async": true,
          "exportedName": "removeCardsByTag",
          "filename": "src/app/actions/manage.ts"
        }
      },
      "exportedName": "removeCardsByTag",
      "filename": "src/app/actions/manage.ts"
    },
    "78ad598f8e4c533188297c867091758ea51a1af89f": {
      "workers": {
        "app/card/manage/page": {
          "moduleId": 842951,
          "async": true,
          "exportedName": "copyCardsByTag",
          "filename": "src/app/actions/manage.ts"
        }
      },
      "exportedName": "copyCardsByTag",
      "filename": "src/app/actions/manage.ts"
    }
  },
  "edge": {}
}