{
  "node": {
    "404b5cf174cbf3f9a2603ffa3527b6623e54aaa717": {
      "workers": {
        "app/blog/[uuid]/page": {
          "moduleId": 759587,
          "async": true,
          "exportedName": "getKey",
          "filename": "src/app/actions/settings_general.ts"
        }
      },
      "exportedName": "getKey",
      "filename": "src/app/actions/settings_general.ts"
    },
    "6010b3e09ee4e9e91fc83c4656c63a9967ff9bb609": {
      "workers": {
        "app/blog/[uuid]/page": {
          "moduleId": 759587,
          "async": true,
          "exportedName": "callSTT",
          "filename": "src/app/actions/ai_local_redis.ts"
        }
      },
      "exportedName": "callSTT",
      "filename": "src/app/actions/ai_local_redis.ts"
    },
    "60bcb6ddbb06ebc22a07ba08e0b065f704db907a1a": {
      "workers": {
        "app/blog/[uuid]/page": {
          "moduleId": 759587,
          "async": true,
          "exportedName": "callSTT",
          "filename": "src/app/actions/ai_gemini.ts"
        }
      },
      "exportedName": "callSTT",
      "filename": "src/app/actions/ai_gemini.ts"
    },
    "601839830f00e32c5906f90e6545267d97634f3fc1": {
      "workers": {
        "app/blog/[uuid]/page": {
          "moduleId": 759587,
          "async": true,
          "exportedName": "callTTS",
          "filename": "src/app/actions/ai_gemini.ts"
        }
      },
      "exportedName": "callTTS",
      "filename": "src/app/actions/ai_gemini.ts"
    },
    "40a638ef82933964c0207f524cf13d10947300c60f": {
      "workers": {
        "app/blog/[uuid]/page": {
          "moduleId": 759587,
          "async": true,
          "exportedName": "getCardsByQuestionHashes",
          "filename": "src/app/actions/card.ts"
        }
      },
      "exportedName": "getCardsByQuestionHashes",
      "filename": "src/app/actions/card.ts"
    },
    "4099bed208c815c8a1577c86f68d0590f46bbc8e2e": {
      "workers": {
        "app/blog/[uuid]/page": {
          "moduleId": 759587,
          "async": true,
          "exportedName": "saveCard",
          "filename": "src/app/actions/card.ts"
        }
      },
      "exportedName": "saveCard",
      "filename": "src/app/actions/card.ts"
    },
    "40a42e8acbbf6e5b95d4a97e4c99f67cd7a7923ca6": {
      "workers": {
        "app/blog/[uuid]/page": {
          "moduleId": 759587,
          "async": true,
          "exportedName": "saveCardTag",
          "filename": "src/app/actions/card.ts"
        }
      },
      "exportedName": "saveCardTag",
      "filename": "src/app/actions/card.ts"
    },
    "005171974638f5bee5357c48e8e5a6b294889608f6": {
      "workers": {
        "app/blog/[uuid]/page": {
          "moduleId": 759587,
          "async": true,
          "exportedName": "deleteAuthTokens",
          "filename": "src/app/actions/auth.ts"
        }
      },
      "exportedName": "deleteAuthTokens",
      "filename": "src/app/actions/auth.ts"
    },
    "40629947780d9ef7b6c6b076ac84f942a3df934f76": {
      "workers": {
        "app/blog/[uuid]/page": {
          "moduleId": 759587,
          "async": true,
          "exportedName": "getPlanAll",
          "filename": "src/app/actions/plan.ts"
        }
      },
      "exportedName": "getPlanAll",
      "filename": "src/app/actions/plan.ts"
    },
    "4028e64f2b3b73dcdbec12667c5e0411aa3a76b2c1": {
      "workers": {
        "app/blog/[uuid]/page": {
          "moduleId": 759587,
          "async": true,
          "exportedName": "saveRecord",
          "filename": "src/app/actions/plan.ts"
        }
      },
      "exportedName": "saveRecord",
      "filename": "src/app/actions/plan.ts"
    },
    "4029035e56f048fc67e75f281470f563e8bfcba43e": {
      "workers": {
        "app/blog/[uuid]/page": {
          "moduleId": 759587,
          "async": true,
          "exportedName": "saveBlog",
          "filename": "src/app/actions/blog.ts"
        }
      },
      "exportedName": "saveBlog",
      "filename": "src/app/actions/blog.ts"
    },
    "402b92c7d93a0630e1f67547090ba70c45dcd4f92d": {
      "workers": {
        "app/blog/[uuid]/page": {
          "moduleId": 759587,
          "async": true,
          "exportedName": "getBlog",
          "filename": "src/app/actions/blog.ts"
        }
      },
      "exportedName": "getBlog",
      "filename": "src/app/actions/blog.ts"
    },
    "404b47c3ed700d8a0553d2e0c5028394401b6fe151": {
      "workers": {
        "app/blog/[uuid]/page": {
          "moduleId": 759587,
          "async": true,
          "exportedName": "getBlogAllOfAnother",
          "filename": "src/app/actions/blog.ts"
        }
      },
      "exportedName": "getBlogAllOfAnother",
      "filename": "src/app/actions/blog.ts"
    },
    "408562cf97c5e00099cdf940cc416ed0a2a65d04dd": {
      "workers": {
        "app/blog/[uuid]/page": {
          "moduleId": 759587,
          "async": true,
          "exportedName": "getBlogAll",
          "filename": "src/app/actions/blog.ts"
        }
      },
      "exportedName": "getBlogAll",
      "filename": "src/app/actions/blog.ts"
    },
    "40db1091eadf0e0c4cd9ddb1aa0b865f753282369c": {
      "workers": {
        "app/blog/[uuid]/page": {
          "moduleId": 759587,
          "async": true,
          "exportedName": "getBlogAllOfOthers",
          "filename": "src/app/actions/blog.ts"
        }
      },
      "exportedName": "getBlogAllOfOthers",
      "filename": "src/app/actions/blog.ts"
    }
  },
  "edge": {}
}