{
  "node": {
    "0055ae5d73451da555238d25494a0f48f35dbefe69": {
      "workers": {
        "app/blog/[uuid]/page": {
          "moduleId": "7130",
          "async": false,
          "exportedName": "initCmdMap",
          "filename": "src/app/actions/voice_access.ts"
        }
      },
      "layer": {
        "app/blog/[uuid]/page": "action-browser"
      },
      "exportedName": "initCmdMap",
      "filename": "src/app/actions/voice_access.ts"
    },
    "40562711aaf7e607f748a2d3473dc9be5a44b0fff8": {
      "workers": {
        "app/blog/[uuid]/page": {
          "moduleId": "7130",
          "async": false,
          "exportedName": "callSTT",
          "filename": "src/app/actions/ai_local_redis.ts"
        }
      },
      "layer": {
        "app/blog/[uuid]/page": "action-browser"
      },
      "exportedName": "callSTT",
      "filename": "src/app/actions/ai_local_redis.ts"
    },
    "4087cb42e9d9487b0b675540f3cc976cd5661bafb0": {
      "workers": {
        "app/blog/[uuid]/page": {
          "moduleId": "7130",
          "async": false,
          "exportedName": "callSTT",
          "filename": "src/app/actions/ai_gemini.ts"
        }
      },
      "layer": {
        "app/blog/[uuid]/page": "action-browser"
      },
      "exportedName": "callSTT",
      "filename": "src/app/actions/ai_gemini.ts"
    },
    "60e0224e4e69d2f8461589183fed3a9820c0bc9536": {
      "workers": {
        "app/blog/[uuid]/page": {
          "moduleId": "7130",
          "async": false,
          "exportedName": "callTTS",
          "filename": "src/app/actions/ai_gemini.ts"
        }
      },
      "layer": {
        "app/blog/[uuid]/page": "action-browser"
      },
      "exportedName": "callTTS",
      "filename": "src/app/actions/ai_gemini.ts"
    },
    "00012d514da3d08191a712eb6a3eb8ff61660ebf34": {
      "workers": {
        "app/blog/[uuid]/page": {
          "moduleId": "7130",
          "async": false,
          "exportedName": "initCmdHelpMap",
          "filename": "src/app/actions/voice_access.ts"
        }
      },
      "layer": {
        "app/blog/[uuid]/page": "action-browser"
      },
      "exportedName": "initCmdHelpMap",
      "filename": "src/app/actions/voice_access.ts"
    },
    "40a8aa7fd08ed42b78a83037260c5fd3846604e216": {
      "workers": {
        "app/blog/[uuid]/page": {
          "moduleId": "7130",
          "async": false,
          "exportedName": "saveBlog",
          "filename": "src/app/actions/blog.ts"
        }
      },
      "layer": {
        "app/blog/[uuid]/page": "rsc"
      },
      "exportedName": "saveBlog",
      "filename": "src/app/actions/blog.ts"
    },
    "404818c41983692d55b619c9ef7aaa903ef30f2dd9": {
      "workers": {
        "app/blog/[uuid]/page": {
          "moduleId": "7130",
          "async": false,
          "exportedName": "getBlogAll",
          "filename": "src/app/actions/blog.ts"
        }
      },
      "layer": {
        "app/blog/[uuid]/page": "rsc"
      },
      "exportedName": "getBlogAll",
      "filename": "src/app/actions/blog.ts"
    },
    "407019448d795043bc3fd472c20ca91ede3d5fe889": {
      "workers": {
        "app/blog/[uuid]/page": {
          "moduleId": "7130",
          "async": false,
          "exportedName": "getBlogAllOfAnother",
          "filename": "src/app/actions/blog.ts"
        }
      },
      "layer": {
        "app/blog/[uuid]/page": "rsc"
      },
      "exportedName": "getBlogAllOfAnother",
      "filename": "src/app/actions/blog.ts"
    },
    "40c220f6bc893508ee1a4e97117704338a03ba6658": {
      "workers": {
        "app/blog/[uuid]/page": {
          "moduleId": "7130",
          "async": false,
          "exportedName": "getBlog",
          "filename": "src/app/actions/blog.ts"
        }
      },
      "layer": {
        "app/blog/[uuid]/page": "rsc"
      },
      "exportedName": "getBlog",
      "filename": "src/app/actions/blog.ts"
    },
    "40dcf18769cd1d8d486f76af58b9e42f0e7ff6739c": {
      "workers": {
        "app/blog/[uuid]/page": {
          "moduleId": "7130",
          "async": false,
          "exportedName": "getBlogAllOfOthers",
          "filename": "src/app/actions/blog.ts"
        }
      },
      "layer": {
        "app/blog/[uuid]/page": "rsc"
      },
      "exportedName": "getBlogAllOfOthers",
      "filename": "src/app/actions/blog.ts"
    }
  },
  "edge": {}
}