{
  "node": {
    "0086dc8c6dd3169a7f195458320d3b3a01a6138076": {
      "workers": {
        "app/card/my/page": {
          "moduleId": "98262",
          "async": false,
          "exportedName": "initCmdMap",
          "filename": "src/app/actions/voice_access.ts"
        }
      },
      "layer": {
        "app/card/my/page": "action-browser"
      },
      "exportedName": "initCmdMap",
      "filename": "src/app/actions/voice_access.ts"
    },
    "40cbdcadafeaa20b02489a949c266e90ec6029fe6e": {
      "workers": {
        "app/card/my/page": {
          "moduleId": "98262",
          "async": false,
          "exportedName": "callSTT",
          "filename": "src/app/actions/ai_local_redis.ts"
        }
      },
      "layer": {
        "app/card/my/page": "action-browser"
      },
      "exportedName": "callSTT",
      "filename": "src/app/actions/ai_local_redis.ts"
    },
    "407a315972ede2ccfa42235449ae46cb45143db184": {
      "workers": {
        "app/card/my/page": {
          "moduleId": "98262",
          "async": false,
          "exportedName": "callSTT",
          "filename": "src/app/actions/ai_gemini.ts"
        }
      },
      "layer": {
        "app/card/my/page": "action-browser"
      },
      "exportedName": "callSTT",
      "filename": "src/app/actions/ai_gemini.ts"
    },
    "60c1dea2108fc0037662d43964c624662d160d166b": {
      "workers": {
        "app/card/my/page": {
          "moduleId": "98262",
          "async": false,
          "exportedName": "callTTS",
          "filename": "src/app/actions/ai_gemini.ts"
        }
      },
      "layer": {
        "app/card/my/page": "action-browser"
      },
      "exportedName": "callTTS",
      "filename": "src/app/actions/ai_gemini.ts"
    },
    "0070497fef0d6bfd50d95de6e5d747e8ccce8eb0af": {
      "workers": {
        "app/card/my/page": {
          "moduleId": "98262",
          "async": false,
          "exportedName": "initCmdHelpMap",
          "filename": "src/app/actions/voice_access.ts"
        }
      },
      "layer": {
        "app/card/my/page": "action-browser"
      },
      "exportedName": "initCmdHelpMap",
      "filename": "src/app/actions/voice_access.ts"
    },
    "40b5d98791a078249965f731345295fecd33b84cb2": {
      "workers": {
        "app/card/my/page": {
          "moduleId": "98262",
          "async": false,
          "exportedName": "getTagAll",
          "filename": "src/app/actions/card.ts"
        }
      },
      "layer": {
        "app/card/my/page": "rsc"
      },
      "exportedName": "getTagAll",
      "filename": "src/app/actions/card.ts"
    },
    "40b8ed30ed88a2ec253bf24e431c8b615cd1563a7c": {
      "workers": {
        "app/card/my/page": {
          "moduleId": "98262",
          "async": false,
          "exportedName": "saveCard",
          "filename": "src/app/actions/card.ts"
        }
      },
      "layer": {
        "app/card/my/page": "rsc"
      },
      "exportedName": "saveCard",
      "filename": "src/app/actions/card.ts"
    },
    "4018cdf6a37c2e72c21a97426e63e381152d4c7c61": {
      "workers": {
        "app/card/my/page": {
          "moduleId": "98262",
          "async": false,
          "exportedName": "saveCardTag",
          "filename": "src/app/actions/card.ts"
        }
      },
      "layer": {
        "app/card/my/page": "rsc"
      },
      "exportedName": "saveCardTag",
      "filename": "src/app/actions/card.ts"
    },
    "604110ce8679e8c7ee7bc4ae4966c1929d06191197": {
      "workers": {
        "app/card/my/page": {
          "moduleId": "98262",
          "async": false,
          "exportedName": "getCardTag",
          "filename": "src/app/actions/card.ts"
        }
      },
      "layer": {
        "app/card/my/page": "rsc"
      },
      "exportedName": "getCardTag",
      "filename": "src/app/actions/card.ts"
    },
    "60b91acb9e6bd5781f0634d1ddecc0c3cccf9d359f": {
      "workers": {
        "app/card/my/page": {
          "moduleId": "98262",
          "async": false,
          "exportedName": "setCardFamiliarity",
          "filename": "src/app/actions/card.ts"
        }
      },
      "layer": {
        "app/card/my/page": "rsc"
      },
      "exportedName": "setCardFamiliarity",
      "filename": "src/app/actions/card.ts"
    },
    "7e6441e25e00621c6442ab6af2bd2f765373703ce6": {
      "workers": {
        "app/card/my/page": {
          "moduleId": "98262",
          "async": false,
          "exportedName": "getCardAll",
          "filename": "src/app/actions/card.ts"
        }
      },
      "layer": {
        "app/card/my/page": "rsc"
      },
      "exportedName": "getCardAll",
      "filename": "src/app/actions/card.ts"
    },
    "40026cf22cc7e092082c0e468c60e1be1536bee58b": {
      "workers": {
        "app/card/my/page": {
          "moduleId": "98262",
          "async": false,
          "exportedName": "createTag",
          "filename": "src/app/actions/card.ts"
        }
      },
      "layer": {
        "app/card/my/page": "rsc"
      },
      "exportedName": "createTag",
      "filename": "src/app/actions/card.ts"
    },
    "402f1091aefd551bd4479c2ad19f29727c4a9f6ca6": {
      "workers": {
        "app/card/my/page": {
          "moduleId": "98262",
          "async": false,
          "exportedName": "saveTag",
          "filename": "src/app/actions/card.ts"
        }
      },
      "layer": {
        "app/card/my/page": "rsc"
      },
      "exportedName": "saveTag",
      "filename": "src/app/actions/card.ts"
    },
    "404720144852f294c45450d3f32556fbd472ceeef4": {
      "workers": {
        "app/card/my/page": {
          "moduleId": "98262",
          "async": false,
          "exportedName": "removeTag",
          "filename": "src/app/actions/card.ts"
        }
      },
      "layer": {
        "app/card/my/page": "rsc"
      },
      "exportedName": "removeTag",
      "filename": "src/app/actions/card.ts"
    },
    "404cfeb8aec3db4a220260d7c18a8abcc336af7ce7": {
      "workers": {
        "app/card/my/page": {
          "moduleId": "98262",
          "async": false,
          "exportedName": "saveCardReview",
          "filename": "src/app/actions/card.ts"
        }
      },
      "layer": {
        "app/card/my/page": "rsc"
      },
      "exportedName": "saveCardReview",
      "filename": "src/app/actions/card.ts"
    },
    "409b1bbf1fbad0abc1dd4ef3b42e4627d1e51d94cc": {
      "workers": {
        "app/card/my/page": {
          "moduleId": "98262",
          "async": false,
          "exportedName": "getTag",
          "filename": "src/app/actions/card.ts"
        }
      },
      "layer": {
        "app/card/my/page": "rsc"
      },
      "exportedName": "getTag",
      "filename": "src/app/actions/card.ts"
    },
    "40a7127396dc2de20a9dcb11973385dcd328c8a54a": {
      "workers": {
        "app/card/my/page": {
          "moduleId": "98262",
          "async": false,
          "exportedName": "getCard",
          "filename": "src/app/actions/card.ts"
        }
      },
      "layer": {
        "app/card/my/page": "rsc"
      },
      "exportedName": "getCard",
      "filename": "src/app/actions/card.ts"
    },
    "40c24a674b68334f2c687fcadc7e8827c694020f4d": {
      "workers": {
        "app/card/my/page": {
          "moduleId": "98262",
          "async": false,
          "exportedName": "getCardTestByUUID",
          "filename": "src/app/actions/card.ts"
        }
      },
      "layer": {
        "app/card/my/page": "rsc"
      },
      "exportedName": "getCardTestByUUID",
      "filename": "src/app/actions/card.ts"
    },
    "40d860be20c90c984f0f88f413a9fc57d7c2304b50": {
      "workers": {
        "app/card/my/page": {
          "moduleId": "98262",
          "async": false,
          "exportedName": "removeCard",
          "filename": "src/app/actions/card.ts"
        }
      },
      "layer": {
        "app/card/my/page": "rsc"
      },
      "exportedName": "removeCard",
      "filename": "src/app/actions/card.ts"
    },
    "6084544e35e2c1a8f79c0233fa8643cf0d61f7c3c3": {
      "workers": {
        "app/card/my/page": {
          "moduleId": "98262",
          "async": false,
          "exportedName": "getCardTest",
          "filename": "src/app/actions/card.ts"
        }
      },
      "layer": {
        "app/card/my/page": "rsc"
      },
      "exportedName": "getCardTest",
      "filename": "src/app/actions/card.ts"
    }
  },
  "edge": {}
}