{
  "node": {
    "406fabbdedea16a58105e442d8e4c62f33d61386e3": {
      "workers": {
        "app/plan/page": {
          "moduleId": 643006,
          "async": true,
          "exportedName": "getKey",
          "filename": "src/app/actions/settings_general.ts"
        }
      },
      "exportedName": "getKey",
      "filename": "src/app/actions/settings_general.ts"
    },
    "60092b584e42f137730cb77b97c5f53cc96087e93f": {
      "workers": {
        "app/plan/page": {
          "moduleId": 643006,
          "async": true,
          "exportedName": "callSTT",
          "filename": "src/app/actions/ai_local_redis.ts"
        }
      },
      "exportedName": "callSTT",
      "filename": "src/app/actions/ai_local_redis.ts"
    },
    "60757008ce7830ba2fe7b31f42306486ea8248591b": {
      "workers": {
        "app/plan/page": {
          "moduleId": 643006,
          "async": true,
          "exportedName": "callSTT",
          "filename": "src/app/actions/ai_gemini.ts"
        }
      },
      "exportedName": "callSTT",
      "filename": "src/app/actions/ai_gemini.ts"
    },
    "600257717b332621d14d8a1b13dfd559be8149fa56": {
      "workers": {
        "app/plan/page": {
          "moduleId": 643006,
          "async": true,
          "exportedName": "callTTS",
          "filename": "src/app/actions/ai_gemini.ts"
        }
      },
      "exportedName": "callTTS",
      "filename": "src/app/actions/ai_gemini.ts"
    },
    "40f864cf031a26a5f1c096d5572f84e6358ad8b045": {
      "workers": {
        "app/plan/page": {
          "moduleId": 643006,
          "async": true,
          "exportedName": "saveCard",
          "filename": "src/app/actions/card.ts"
        }
      },
      "exportedName": "saveCard",
      "filename": "src/app/actions/card.ts"
    },
    "40ec137112de39a1c8ef54a6692160fbca81a8e4e8": {
      "workers": {
        "app/plan/page": {
          "moduleId": 643006,
          "async": true,
          "exportedName": "saveCardTag",
          "filename": "src/app/actions/card.ts"
        }
      },
      "exportedName": "saveCardTag",
      "filename": "src/app/actions/card.ts"
    },
    "00f20b49969d253f7c0a34591578e9c213e1a1c3af": {
      "workers": {
        "app/plan/page": {
          "moduleId": 643006,
          "async": true,
          "exportedName": "deleteAuthTokens",
          "filename": "src/app/actions/auth.ts"
        }
      },
      "exportedName": "deleteAuthTokens",
      "filename": "src/app/actions/auth.ts"
    },
    "40026e4bb1b399960e6791365f9d33f4d6e040a825": {
      "workers": {
        "app/plan/page": {
          "moduleId": 643006,
          "async": true,
          "exportedName": "getPlanAll",
          "filename": "src/app/actions/plan.ts"
        }
      },
      "exportedName": "getPlanAll",
      "filename": "src/app/actions/plan.ts"
    },
    "40784585b47acc2f9cfe4fa10ffdef404266e28877": {
      "workers": {
        "app/plan/page": {
          "moduleId": 643006,
          "async": true,
          "exportedName": "removePlan",
          "filename": "src/app/actions/plan.ts"
        }
      },
      "exportedName": "removePlan",
      "filename": "src/app/actions/plan.ts"
    },
    "4050dd440ae363f4a755e1435f4e8fd5723f27ef5b": {
      "workers": {
        "app/plan/page": {
          "moduleId": 643006,
          "async": true,
          "exportedName": "savePlan",
          "filename": "src/app/actions/plan.ts"
        }
      },
      "exportedName": "savePlan",
      "filename": "src/app/actions/plan.ts"
    },
    "40078b13fe9a4414d2abed35dd560ea27e43f03871": {
      "workers": {
        "app/plan/page": {
          "moduleId": 643006,
          "async": true,
          "exportedName": "getRecordAll",
          "filename": "src/app/actions/plan.ts"
        }
      },
      "exportedName": "getRecordAll",
      "filename": "src/app/actions/plan.ts"
    },
    "40043ac2160e5d28d5f0df3bee05d8508d49691f76": {
      "workers": {
        "app/plan/page": {
          "moduleId": 643006,
          "async": true,
          "exportedName": "saveRecord",
          "filename": "src/app/actions/plan.ts"
        }
      },
      "exportedName": "saveRecord",
      "filename": "src/app/actions/plan.ts"
    }
  },
  "edge": {}
}