{
  "node": {
    "608c9742570db9ca26467eba883e885026864e83e6": {
      "workers": {
        "app/card/improve/page": {
          "moduleId": 993972,
          "async": true,
          "exportedName": "callSTT",
          "filename": "src/app/actions/ai_local_redis.ts"
        }
      },
      "exportedName": "callSTT",
      "filename": "src/app/actions/ai_local_redis.ts"
    },
    "60584625744e1b3be70f1daae9e9beafbb91233f70": {
      "workers": {
        "app/card/improve/page": {
          "moduleId": 993972,
          "async": true,
          "exportedName": "callSTT",
          "filename": "src/app/actions/ai_gemini.ts"
        }
      },
      "exportedName": "callSTT",
      "filename": "src/app/actions/ai_gemini.ts"
    },
    "60a84a7c291a4e43355e648d3354ed65e4086be0f1": {
      "workers": {
        "app/card/improve/page": {
          "moduleId": 993972,
          "async": true,
          "exportedName": "callTTS",
          "filename": "src/app/actions/ai_gemini.ts"
        }
      },
      "exportedName": "callTTS",
      "filename": "src/app/actions/ai_gemini.ts"
    },
    "4069477bd4013c98979315ab35ec658e802cf0d003": {
      "workers": {
        "app/card/improve/page": {
          "moduleId": 993972,
          "async": true,
          "exportedName": "getKey",
          "filename": "src/app/actions/settings_general.ts"
        }
      },
      "exportedName": "getKey",
      "filename": "src/app/actions/settings_general.ts"
    },
    "404b8f078fea3fca5be0f56245e84a98140bb8cde0": {
      "workers": {
        "app/card/improve/page": {
          "moduleId": 993972,
          "async": true,
          "exportedName": "saveCard",
          "filename": "src/app/actions/card.ts"
        }
      },
      "exportedName": "saveCard",
      "filename": "src/app/actions/card.ts"
    },
    "40791c5e704b87c1f7622ea5101d9263e358c3363e": {
      "workers": {
        "app/card/improve/page": {
          "moduleId": 993972,
          "async": true,
          "exportedName": "saveCardTag",
          "filename": "src/app/actions/card.ts"
        }
      },
      "exportedName": "saveCardTag",
      "filename": "src/app/actions/card.ts"
    },
    "00aa9f5875d5db9bc1ea4fb96c830922404bf1664d": {
      "workers": {
        "app/card/improve/page": {
          "moduleId": 993972,
          "async": true,
          "exportedName": "deleteAuthTokens",
          "filename": "src/app/actions/auth.ts"
        }
      },
      "exportedName": "deleteAuthTokens",
      "filename": "src/app/actions/auth.ts"
    },
    "787549b737b4852ba0c7e70662666c001877a0a3e7": {
      "workers": {
        "app/card/improve/page": {
          "moduleId": 993972,
          "async": true,
          "exportedName": "getCardImproveAll",
          "filename": "src/app/actions/card_improve.ts"
        }
      },
      "exportedName": "getCardImproveAll",
      "filename": "src/app/actions/card_improve.ts"
    },
    "40460e440dee4f717944d66ce8859c72f139b31f3a": {
      "workers": {
        "app/card/improve/page": {
          "moduleId": 993972,
          "async": true,
          "exportedName": "getCardsNeedImprove",
          "filename": "src/app/actions/card_improve.ts"
        }
      },
      "exportedName": "getCardsNeedImprove",
      "filename": "src/app/actions/card_improve.ts"
    },
    "406ec27da47ae6dc458941e4c03fa9ce6ad8e0ae1c": {
      "workers": {
        "app/card/improve/page": {
          "moduleId": 993972,
          "async": true,
          "exportedName": "applyCardImprove",
          "filename": "src/app/actions/card_improve.ts"
        }
      },
      "exportedName": "applyCardImprove",
      "filename": "src/app/actions/card_improve.ts"
    },
    "409b426c0350f36a536f0ffdc33d0357446109f6c7": {
      "workers": {
        "app/card/improve/page": {
          "moduleId": 993972,
          "async": true,
          "exportedName": "rejectCardImprove",
          "filename": "src/app/actions/card_improve.ts"
        }
      },
      "exportedName": "rejectCardImprove",
      "filename": "src/app/actions/card_improve.ts"
    },
    "40869b117135e56d9922dcfd1cd87496682cbf2e2b": {
      "workers": {
        "app/card/improve/page": {
          "moduleId": 993972,
          "async": true,
          "exportedName": "getCardImproveStats",
          "filename": "src/app/actions/card_improve.ts"
        }
      },
      "exportedName": "getCardImproveStats",
      "filename": "src/app/actions/card_improve.ts"
    }
  },
  "edge": {}
}