{
  "node": {
    "006536be8303bf9b88e248a11bc479cae252d48501": {
      "workers": {
        "app/speak/practice/page": {
          "moduleId": 571931,
          "async": true,
          "exportedName": "getTextAll",
          "filename": "src/app/actions/practice.ts"
        }
      },
      "exportedName": "getTextAll",
      "filename": "src/app/actions/practice.ts"
    },
    "402fbc808afe6960524d1836b7c24356c399ec7680": {
      "workers": {
        "app/speak/practice/page": {
          "moduleId": 571931,
          "async": true,
          "exportedName": "removeText",
          "filename": "src/app/actions/practice.ts"
        }
      },
      "exportedName": "removeText",
      "filename": "src/app/actions/practice.ts"
    },
    "40c57fafd7fd0f6acd43eee4572e96ca514857d42e": {
      "workers": {
        "app/speak/practice/page": {
          "moduleId": 571931,
          "async": true,
          "exportedName": "saveText",
          "filename": "src/app/actions/practice.ts"
        }
      },
      "exportedName": "saveText",
      "filename": "src/app/actions/practice.ts"
    }
  },
  "edge": {}
}