{
  "node": {
    "40df56eaddd4481d86e82ff897c64cc53085e5a3e2": {
      "workers": {
        "app/dataset/tag/page": {
          "moduleId": 857471,
          "async": true,
          "exportedName": "getKey",
          "filename": "src/app/actions/settings_general.ts"
        }
      },
      "exportedName": "getKey",
      "filename": "src/app/actions/settings_general.ts"
    },
    "6017bff979434106e398c219f4ff9a791e00492974": {
      "workers": {
        "app/dataset/tag/page": {
          "moduleId": 857471,
          "async": true,
          "exportedName": "callSTT",
          "filename": "src/app/actions/ai_local_redis.ts"
        }
      },
      "exportedName": "callSTT",
      "filename": "src/app/actions/ai_local_redis.ts"
    },
    "60ebe09be4004c4efe6f5bd8ed5ea6ef819bea2b58": {
      "workers": {
        "app/dataset/tag/page": {
          "moduleId": 857471,
          "async": true,
          "exportedName": "callSTT",
          "filename": "src/app/actions/ai_gemini.ts"
        }
      },
      "exportedName": "callSTT",
      "filename": "src/app/actions/ai_gemini.ts"
    },
    "40b8b3dacc305cf0257fbc11baf2cb3d15a29ef66e": {
      "workers": {
        "app/dataset/tag/page": {
          "moduleId": 857471,
          "async": true,
          "exportedName": "generateInterviewAnswer",
          "filename": "src/app/actions/ai_gemini.ts"
        }
      },
      "exportedName": "generateInterviewAnswer",
      "filename": "src/app/actions/ai_gemini.ts"
    },
    "60c34e6c77e974a5391a7eabc349f7ebc32a4d2c67": {
      "workers": {
        "app/dataset/tag/page": {
          "moduleId": 857471,
          "async": true,
          "exportedName": "callTTS",
          "filename": "src/app/actions/ai_gemini.ts"
        }
      },
      "exportedName": "callTTS",
      "filename": "src/app/actions/ai_gemini.ts"
    },
    "40516a66ca504a4f3bfbe990a33ee2a5e5ca00f6b4": {
      "workers": {
        "app/dataset/tag/page": {
          "moduleId": 857471,
          "async": true,
          "exportedName": "getCardsByQuestionHashes",
          "filename": "src/app/actions/card.ts"
        }
      },
      "exportedName": "getCardsByQuestionHashes",
      "filename": "src/app/actions/card.ts"
    },
    "40bdd3a08122e7386e0d3182d56b51edaa0f58b1fb": {
      "workers": {
        "app/dataset/tag/page": {
          "moduleId": 857471,
          "async": true,
          "exportedName": "saveCard",
          "filename": "src/app/actions/card.ts"
        }
      },
      "exportedName": "saveCard",
      "filename": "src/app/actions/card.ts"
    },
    "4005b5342a9107fafdaf438208612c265ac0630cee": {
      "workers": {
        "app/dataset/tag/page": {
          "moduleId": 857471,
          "async": true,
          "exportedName": "saveCardTag",
          "filename": "src/app/actions/card.ts"
        }
      },
      "exportedName": "saveCardTag",
      "filename": "src/app/actions/card.ts"
    },
    "00a9423370e2fa229fcc569cbb646dfc7587a92387": {
      "workers": {
        "app/dataset/tag/page": {
          "moduleId": 857471,
          "async": true,
          "exportedName": "deleteAuthTokens",
          "filename": "src/app/actions/auth.ts"
        }
      },
      "exportedName": "deleteAuthTokens",
      "filename": "src/app/actions/auth.ts"
    },
    "40e0ebdc89b9e9380275b424c19f5f81435de89816": {
      "workers": {
        "app/dataset/tag/page": {
          "moduleId": 857471,
          "async": true,
          "exportedName": "getPlanAll",
          "filename": "src/app/actions/plan.ts"
        }
      },
      "exportedName": "getPlanAll",
      "filename": "src/app/actions/plan.ts"
    },
    "4013c7d0314dabde1a8d2f3985b1eb88df5765d002": {
      "workers": {
        "app/dataset/tag/page": {
          "moduleId": 857471,
          "async": true,
          "exportedName": "saveRecord",
          "filename": "src/app/actions/plan.ts"
        }
      },
      "exportedName": "saveRecord",
      "filename": "src/app/actions/plan.ts"
    },
    "6028bcb219d414bd468a3f173c503ee7b28c9181f1": {
      "workers": {
        "app/dataset/tag/page": {
          "moduleId": 857471,
          "async": true,
          "exportedName": "getTagAllOwned",
          "filename": "src/app/actions/dataset.ts"
        }
      },
      "exportedName": "getTagAllOwned",
      "filename": "src/app/actions/dataset.ts"
    },
    "4012941bf12df8c5c69aa7ae1a7c83f8dc4aec52f2": {
      "workers": {
        "app/dataset/tag/page": {
          "moduleId": 857471,
          "async": true,
          "exportedName": "removeTag",
          "filename": "src/app/actions/dataset.ts"
        }
      },
      "exportedName": "removeTag",
      "filename": "src/app/actions/dataset.ts"
    },
    "40f4861eab6f70641d832c8852baf48c081090792a": {
      "workers": {
        "app/dataset/tag/page": {
          "moduleId": 857471,
          "async": true,
          "exportedName": "saveTag",
          "filename": "src/app/actions/dataset.ts"
        }
      },
      "exportedName": "saveTag",
      "filename": "src/app/actions/dataset.ts"
    },
    "00365ed6e362a79eefe0ac3ef0ce59f160d3f83666": {
      "workers": {
        "app/dataset/tag/page": {
          "moduleId": 857471,
          "async": true,
          "exportedName": "getAllScopes",
          "filename": "src/app/actions/dataset.ts"
        }
      },
      "exportedName": "getAllScopes",
      "filename": "src/app/actions/dataset.ts"
    },
    "403906995787e4c417d4c60cd3211438943f11d844": {
      "workers": {
        "app/dataset/tag/page": {
          "moduleId": 857471,
          "async": true,
          "exportedName": "getTagScopeMap",
          "filename": "src/app/actions/dataset.ts"
        }
      },
      "exportedName": "getTagScopeMap",
      "filename": "src/app/actions/dataset.ts"
    },
    "6000bcdc50b6bb7128e115808bb5480738ba080e0c": {
      "workers": {
        "app/dataset/tag/page": {
          "moduleId": 857471,
          "async": true,
          "exportedName": "setTagScopes",
          "filename": "src/app/actions/dataset.ts"
        }
      },
      "exportedName": "setTagScopes",
      "filename": "src/app/actions/dataset.ts"
    }
  },
  "edge": {}
}