{
  "node": {
    "00fa9e185af55d781ed4a62e6668020b76e84f4049": {
      "workers": {
        "app/word/top/page": {
          "moduleId": "193409",
          "async": false,
          "exportedName": "initCmdMap",
          "filename": "src/app/actions/voice_access.ts"
        }
      },
      "layer": {
        "app/word/top/page": "action-browser"
      },
      "exportedName": "initCmdMap",
      "filename": "src/app/actions/voice_access.ts"
    },
    "40612a86f977b869a467efc3b11960e773915568b6": {
      "workers": {
        "app/word/top/page": {
          "moduleId": "193409",
          "async": false,
          "exportedName": "callSTT",
          "filename": "src/app/actions/ai_local_redis.ts"
        }
      },
      "layer": {
        "app/word/top/page": "action-browser"
      },
      "exportedName": "callSTT",
      "filename": "src/app/actions/ai_local_redis.ts"
    },
    "40e86fb74103a3a60c397e81a897d7dcb93c5df1e4": {
      "workers": {
        "app/word/top/page": {
          "moduleId": "193409",
          "async": false,
          "exportedName": "callSTT",
          "filename": "src/app/actions/ai_gemini.ts"
        }
      },
      "layer": {
        "app/word/top/page": "action-browser"
      },
      "exportedName": "callSTT",
      "filename": "src/app/actions/ai_gemini.ts"
    },
    "60fe3820d0ca2623dab88e6508a569d0ba5fcc11ba": {
      "workers": {
        "app/word/top/page": {
          "moduleId": "193409",
          "async": false,
          "exportedName": "callTTS",
          "filename": "src/app/actions/ai_gemini.ts"
        }
      },
      "layer": {
        "app/word/top/page": "action-browser"
      },
      "exportedName": "callTTS",
      "filename": "src/app/actions/ai_gemini.ts"
    },
    "002e1d4e9b9f2fedd1797846d2d043760c98fe1962": {
      "workers": {
        "app/word/top/page": {
          "moduleId": "193409",
          "async": false,
          "exportedName": "initCmdHelpMap",
          "filename": "src/app/actions/voice_access.ts"
        }
      },
      "layer": {
        "app/word/top/page": "action-browser"
      },
      "exportedName": "initCmdHelpMap",
      "filename": "src/app/actions/voice_access.ts"
    },
    "7cc49c17606ddce83191b71e3be836fba1f2e5fa8a": {
      "workers": {
        "app/word/top/page": {
          "moduleId": "193409",
          "async": false,
          "exportedName": "getTopword",
          "filename": "src/app/actions/word.ts"
        }
      },
      "layer": {
        "app/word/top/page": "action-browser"
      },
      "exportedName": "getTopword",
      "filename": "src/app/actions/word.ts"
    },
    "7cde9dc8d720ac5b6efd8b28648292df9901fd411c": {
      "workers": {
        "app/word/top/page": {
          "moduleId": "193409",
          "async": false,
          "exportedName": "searchTopword",
          "filename": "src/app/actions/word.ts"
        }
      },
      "layer": {
        "app/word/top/page": "action-browser"
      },
      "exportedName": "searchTopword",
      "filename": "src/app/actions/word.ts"
    },
    "604fa4d2432d93556ca89e3f6e3d9d8389c41e949f": {
      "workers": {
        "app/word/top/page": {
          "moduleId": "193409",
          "async": false,
          "exportedName": "trashWord",
          "filename": "src/app/actions/word.ts"
        }
      },
      "layer": {
        "app/word/top/page": "action-browser"
      },
      "exportedName": "trashWord",
      "filename": "src/app/actions/word.ts"
    },
    "40c9aba8fc374f18d68ee8b3de6d884d813bd5b456": {
      "workers": {
        "app/word/top/page": {
          "moduleId": "193409",
          "async": false,
          "exportedName": "saveCard",
          "filename": "src/app/actions/card.ts"
        }
      },
      "layer": {
        "app/word/top/page": "action-browser"
      },
      "exportedName": "saveCard",
      "filename": "src/app/actions/card.ts"
    },
    "40d3e311b344cb3acc279f12eb663aa42cc315a50f": {
      "workers": {
        "app/word/top/page": {
          "moduleId": "193409",
          "async": false,
          "exportedName": "saveCardTag",
          "filename": "src/app/actions/card.ts"
        }
      },
      "layer": {
        "app/word/top/page": "action-browser"
      },
      "exportedName": "saveCardTag",
      "filename": "src/app/actions/card.ts"
    },
    "40b7bc513d933ea241e6a2324f44274706c4095dc1": {
      "workers": {
        "app/word/top/page": {
          "moduleId": "193409",
          "async": false,
          "exportedName": "getTagAll",
          "filename": "src/app/actions/card.ts"
        }
      },
      "layer": {
        "app/word/top/page": "action-browser"
      },
      "exportedName": "getTagAll",
      "filename": "src/app/actions/card.ts"
    },
    "40370423f63e0399544a0e0df08405e10bb0dff5e7": {
      "workers": {
        "app/word/top/page": {
          "moduleId": "193409",
          "async": false,
          "exportedName": "createTag",
          "filename": "src/app/actions/card.ts"
        }
      },
      "layer": {
        "app/word/top/page": "action-browser"
      },
      "exportedName": "createTag",
      "filename": "src/app/actions/card.ts"
    }
  },
  "edge": {}
}